jupyter_notebook_tracking/__init__.py
jupyter_notebook_tracking/_version.py
jupyter_notebook_tracking/labextension/package.json
jupyter_notebook_tracking/labextension/static/509.c83a4a567f8a315255cd.js
jupyter_notebook_tracking/labextension/static/728.9fd4677cc09131b336b3.js
jupyter_notebook_tracking/labextension/static/remoteEntry.97ed36618b4c4609cf6a.js
jupyter_notebook_tracking/labextension/static/style.js
jupyter_notebook_tracking/labextension/static/third-party-licenses.json
jupyter_notebook_tracking-0.1.1.data/data/share/jupyter/labextensions/jupyter_notebook_tracking/package.json
jupyter_notebook_tracking-0.1.1.data/data/share/jupyter/labextensions/jupyter_notebook_tracking/static/509.c83a4a567f8a315255cd.js
jupyter_notebook_tracking-0.1.1.data/data/share/jupyter/labextensions/jupyter_notebook_tracking/static/728.9fd4677cc09131b336b3.js
jupyter_notebook_tracking-0.1.1.data/data/share/jupyter/labextensions/jupyter_notebook_tracking/static/remoteEntry.97ed36618b4c4609cf6a.js
jupyter_notebook_tracking-0.1.1.data/data/share/jupyter/labextensions/jupyter_notebook_tracking/static/style.js
jupyter_notebook_tracking-0.1.1.data/data/share/jupyter/labextensions/jupyter_notebook_tracking/static/third-party-licenses.json
jupyter_notebook_tracking-0.1.1.data/data/share/jupyter/labextensions/jupyter_notebook_tracking/install.json
jupyter_notebook_tracking-0.1.1.dist-info/METADATA
jupyter_notebook_tracking-0.1.1.dist-info/WHEEL
jupyter_notebook_tracking-0.1.1.dist-info/licenses/LICENSE
jupyter_notebook_tracking-0.1.1.dist-info/RECORD
