Metadata-Version: 2.4
Name: jupyter_notebook_tracking
Version: 0.1.1
Summary: Track total editing time in Jupyter notebooks
Project-URL: Homepage, https://github.com/example/jupyter_notebook_tracking
Project-URL: Bug Tracker, https://github.com/example/jupyter_notebook_tracking/issues
Project-URL: Repository, https://github.com/example/jupyter_notebook_tracking.git
Author: Developer
License: BSD 3-Clause License
License-File: LICENSE
Keywords: jupyter,jupyterlab,jupyterlab-extension
Classifier: Framework :: Jupyter
Classifier: Framework :: Jupyter :: JupyterLab
Classifier: Framework :: Jupyter :: JupyterLab :: 4
Classifier: Framework :: Jupyter :: JupyterLab :: Extensions
Classifier: Framework :: Jupyter :: JupyterLab :: Extensions :: Prebuilt
Classifier: License :: OSI Approved :: BSD License
Classifier: Programming Language :: Python
Classifier: Programming Language :: Python :: 3
Classifier: Programming Language :: Python :: 3.10
Classifier: Programming Language :: Python :: 3.11
Classifier: Programming Language :: Python :: 3.12
Classifier: Programming Language :: Python :: 3.13
Classifier: Programming Language :: Python :: 3.14
Requires-Python: >=3.10
